{
    "id": "fe8904cf-e20e-4884-b829-ed7cec0a01cb",
    "source": 1,
    "name": "@cf/pipecat-ai/smart-turn-v2",
    "description": "An open source, community-driven, native audio turn detection model in 2nd version",
    "task": {
        "id": "ccb1ca5a-043d-41a7-8a3b-61017b2796fd",
        "name": "Voice Activity Detection",
        "description": "Detecting the presence or absence of human speech, used in speech processing."
    },
    "created_at": "2025-08-04 10:08:04.219",
    "tags": [],
    "properties": [
        {
            "property_id": "async_queue",
            "value": "true"
        },
        {
            "property_id": "price",
            "value": [
                {
                    "unit": "per audio minute",
                    "price": 0.00034,
                    "currency": "USD"
                }
            ]
        },
        {
            "property_id": "realtime",
            "value": "true"
        }
    ],
    "schema": {
        "input": {
            "type": "object",
            "oneOf": [
                {
                    "properties": {
                        "audio": {
                            "type": "object",
                            "description": "readable stream with audio data and content-type specified for that data",
                            "properties": {
                                "body": {
                                    "type": "object"
                                },
                                "contentType": {
                                    "type": "string"
                                }
                            },
                            "required": [
                                "body",
                                "contentType"
                            ]
                        },
                        "dtype": {
                            "type": "string",
                            "description": "type of data PCM data that's sent to the inference server as raw array",
                            "enum": [
                                "uint8",
                                "float32",
                                "float64"
                            ]
                        }
                    },
                    "required": [
                        "audio"
                    ]
                },
                {
                    "properties": {
                        "audio": {
                            "type": "string",
                            "description": "base64 encoded audio data"
                        },
                        "dtype": {
                            "type": "string",
                            "description": "type of data PCM data that's sent to the inference server as raw array",
                            "enum": [
                                "uint8",
                                "float32",
                                "float64"
                            ]
                        }
                    },
                    "required": [
                        "audio"
                    ]
                }
            ]
        },
        "output": {
            "type": "object",
            "contentType": "application/json",
            "properties": {
                "is_complete": {
                    "type": "boolean",
                    "description": "if true, end-of-turn was detected"
                },
                "probability": {
                    "type": "number",
                    "description": "probability of the end-of-turn detection"
                }
            }
        }
    }
}